langtask/__init__.py
langtask/api.py
langtask/core/__init__.py
langtask/core/config_loader.py
langtask/core/config_models.py
langtask/core/exceptions.py
langtask/core/file_reader.py
langtask/core/file_validator.py
langtask/core/input_validator.py
langtask/core/llm_connector.py
langtask/core/llm_processor.py
langtask/core/logger.py
langtask/core/output_validator.py
langtask/core/prompt_discoverer.py
langtask/core/prompt_loader.py
langtask/core/prompt_registrar.py
langtask/core/schema_loader.py
langtask-0.1.2.dist-info/LICENSE
langtask-0.1.2.dist-info/METADATA
langtask-0.1.2.dist-info/WHEEL
langtask-0.1.2.dist-info/top_level.txt
langtask-0.1.2.dist-info/RECORD
