Metadata-Version: 2.1
Name: langtask
Version: 0.1.2
Summary: A Python library for structured LLM development with schema validation
Author-email: Kamil Dembinski <kamiltdembinski@gmail.com>
License: MIT
Project-URL: Github, https://github.com/AgeofIA/langtask
Keywords: llm,prompt,anthropic,openai,claude
Classifier: Development Status :: 2 - Pre-Alpha
Classifier: Intended Audience :: Developers
Classifier: License :: OSI Approved :: MIT License
Classifier: Programming Language :: Python :: 3
Classifier: Programming Language :: Python :: 3.10
Classifier: Programming Language :: Python :: 3.11
Classifier: Programming Language :: Python :: 3.12
Classifier: Topic :: Software Development :: Libraries :: Python Modules
Classifier: Topic :: Text Processing :: General
Requires-Python: >=3.10
License-File: LICENSE
Requires-Dist: pyyaml>=6.0
Requires-Dist: pydantic>=2.0
Requires-Dist: python-dotenv>=0.19.0
Requires-Dist: langchain>=0.1.0
Requires-Dist: langchain-openai>=0.0.2
Requires-Dist: langchain-anthropic>=0.1.1
Requires-Dist: loguru>=0.7.0
